README.md
setup.py
src/theia/__init__.py
src/theia/application.py
src/theia/config.py
src/theia/database.py
src/theia/enums.py
src/theia/exceptions.py
src/theia/log.py
src/theia/metaclass.py
src/theia/model.py
src/theia/utils/__init__.py
src/theia/utils/create_project.py
src/theia_api.egg-info/PKG-INFO
src/theia_api.egg-info/SOURCES.txt
src/theia_api.egg-info/dependency_links.txt
src/theia_api.egg-info/entry_points.txt
src/theia_api.egg-info/requires.txt
src/theia_api.egg-info/top_level.txt