Metadata-Version: 2.1
Name: theia-api
Version: 1.0.3
Summary: 基于FastAPI封装通用后台API组件库
Home-page: https://gitee.com/iprintf/theia-api
Author: iprintf
Author-email: iprintf@qq.com
License: Apache
Platform: UNKNOWN
Classifier: Programming Language :: Python :: 3
Classifier: License :: OSI Approved :: Apache Software License
Classifier: Operating System :: OS Independent
Requires-Python: >=3.10
